CHANGELOG.md
geosardine/__init__.py
geosardine/__main__.py
geosardine/_geosardine.py
geosardine/_raster_numba.py
geosardine/_utility.py
geosardine/interpolate/__init__.py
geosardine/interpolate/_utility.py
geosardine/interpolate/idw.py
geosardine/raster.py
geosardine-0.13.1.dist-info/entry_points.txt
geosardine-0.13.1.dist-info/LICENSE.txt
geosardine-0.13.1.dist-info/WHEEL
geosardine-0.13.1.dist-info/METADATA
geosardine-0.13.1.dist-info/RECORD
