Metadata-Version: 2.1
Name: geosardine
Version: 0.13.1
Summary: Spatial operations extend fiona and rasterio
Home-page: https://github.com/sahitono/geosardine
License: BSD-3-Clause
Author: Sahit Tuntas Sadono
Author-email: 26474008+sahitono@users.noreply.github.com
Requires-Python: >=3.7,<3.10
Classifier: Development Status :: 5 - Production/Stable
Classifier: Intended Audience :: Science/Research
Classifier: License :: OSI Approved :: BSD License
Classifier: Programming Language :: Python :: 3
Classifier: Programming Language :: Python :: 3.7
Classifier: Programming Language :: Python :: 3.8
Classifier: Programming Language :: Python :: 3.9
Classifier: Topic :: Scientific/Engineering :: GIS
Classifier: Typing :: Typed
Requires-Dist: affine (>=2.3.0,<3.0.0)
Requires-Dist: click (>=7.1.2,<8.0.0)
Requires-Dist: fiona (>=1.8.13)
Requires-Dist: gdal (>=3.0.4)
Requires-Dist: numba (>=0.51.2)
Requires-Dist: numpy (>=1.18)
Requires-Dist: opencv-python (>=4.4.0,<=5.0.0)
Requires-Dist: pyproj (>=2.6.1)
Requires-Dist: rasterio (>=1.1.2)
Requires-Dist: shapely (>=1.6.4,<2.0.0)
Requires-Dist: tqdm (>=4.48.2,<5.0.0)
Project-URL: Repository, https://github.com/sahitono/geosardine
